LICENSE
MANIFEST.in
README.rst
setup.py
examples/simple.py
github_pushbullet/__init__.py
github_pushbullet.egg-info/PKG-INFO
github_pushbullet.egg-info/SOURCES.txt
github_pushbullet.egg-info/dependency_links.txt
github_pushbullet.egg-info/requires.txt
github_pushbullet.egg-info/top_level.txt