Metadata-Version: 1.1
Name: github-pushbullet
Version: 0.1.1
Summary: Push github notifications to pushbullet.
Home-page: https://github.com/taeguk/github_pushbullet
Author: taeguk
Author-email: xornrbboy@gmail.com
License: MIT
Keywords: github notification push pushbullet
Platform: UNKNOWN
Classifier: Programming Language :: Python :: 3 :: Only
